clackpy/__init__.py
clackpy/prompts.py
clackpy-0.1.0.dist-info/licenses/LICENSE
clackpy-0.1.0.dist-info/METADATA
clackpy-0.1.0.dist-info/WHEEL
clackpy-0.1.0.dist-info/top_level.txt
clackpy-0.1.0.dist-info/RECORD
